{
  "trainingPhrases": [ {
    "parts": [ {
      "text": "reminder ",
      "auto": true
    }, {
      "text": "message",
      "parameterId": "ReminderType",
      "auto": true
    } ],
    "repeatCount": 1,
    "languageCode": "en"
  }, {
    "parts": [ {
      "text": "reminder ",
      "auto": true
    }, {
      "text": "sms",
      "parameterId": "ReminderType",
      "auto": true
    } ],
    "repeatCount": 1,
    "languageCode": "en"
  }, {
    "parts": [ {
      "text": "reminder ",
      "auto": true
    }, {
      "text": "text",
      "parameterId": "ReminderType",
      "auto": true
    } ],
    "repeatCount": 1,
    "languageCode": "en"
  }, {
    "parts": [ {
      "text": "reminder ",
      "auto": true
    }, {
      "text": "call",
      "parameterId": "ReminderType",
      "auto": true
    } ],
    "repeatCount": 1,
    "languageCode": "en"
  }, {
    "parts": [ {
      "text": "schedule a reminder",
      "auto": true
    } ],
    "repeatCount": 1,
    "languageCode": "en"
  }, {
    "parts": [ {
      "text": "can I schedule a reminder",
      "auto": true
    } ],
    "repeatCount": 1,
    "languageCode": "en"
  }, {
    "parts": [ {
      "text": "I need a reminder",
      "auto": true
    } ],
    "repeatCount": 1,
    "languageCode": "en"
  }, {
    "parts": [ {
      "text": "reminder",
      "auto": true
    } ],
    "repeatCount": 1,
    "languageCode": "en"
  }, {
    "parts": [ {
      "text": "I'd like a reminder "
    }, {
      "text": "call",
      "parameterId": "ReminderType"
    } ],
    "repeatCount": 1,
    "languageCode": "en"
  }, {
    "parts": [ {
      "text": "I want a reminder "
    }, {
      "text": "text",
      "parameterId": "ReminderType"
    } ],
    "repeatCount": 1,
    "languageCode": "en"
  }, {
    "parts": [ {
      "text": "I'd like to schedule a reminder for my jury service",
      "auto": true
    } ],
    "repeatCount": 1,
    "languageCode": "en"
  }, {
    "parts": [ {
      "text": "Schedule a reminder",
      "auto": true
    } ],
    "repeatCount": 1,
    "languageCode": "en"
  } ]
}
